{
    "DNDConfig": null,
    "__parentReadjusting__": false,
    "_height_": {
        "type": "string",
        "value": "143dp"
    },
    "_left_": {
        "type": "string",
        "value": "20dp"
    },
    "_margin_": [
        0,
        0,
        0,
        0
    ],
    "_orientation_": 6,
    "_padding_": [
        0,
        0,
        0,
        0
    ],
    "_percent_": true,
    "_right_": {
        "type": "string",
        "value": "20dp"
    },
    "_skin_": "s62a54225a774b8ba8fa95db02c8db35",
    "_top_": {
        "type": "string",
        "value": "295dp"
    },
    "allboxes": [],
    "autogrowmode": 0,
    "canUpdateUI": true,
    "children": [
        "imgPublic",
        "imgPrivate",
        "imgInMem"
    ],
    "clipbounds": true,
    "containerweight": 100,
    "enablescrolling": true,
    "id": "flxCapImg",
    "info": null,
    "iscustomlayout": false,
    "isvisible": true,
    "kuid": "c4decb6b3091438e9351d5ae4730faef",
    "layouttype": 2,
    "name": "kony.ui.FlexContainer",
    "parent": "flxbody",
    "pf": "frmAccessModes",
    "retaincontentalignment": false,
    "retainflexpositionproperties": false,
    "snapgridsize": 10,
    "snaptogrid": true,
    "wType": "FlexContainer",
    "widgetalignment": 1,
    "zindex": 1
}